{
  "has_prev": true,
  "items": [
    {
      "attachment": {},
      "profile_id": "_xjYlxan",
      "author": {
        "status_message": "",
        "active": true,
        "profile_image_url": "",
        "chat_id": "4964159723615736",
        "user_type": 0,
        "nickname": "박수빈",
        "original_profile_image_url": "",
        "id": "4964159723615736_tuser",
        "full_profile_image_url": ""
      },
      "send_at": 1770970931000,
      "id": "3775156559663878146",
      "type": 1,
      "author_id": "4964159723615736_tuser",
      "message": "독해 20개 끝냈어요!",
      "prev_id": "3775156396530618369",
      "chat_id": "4964159723615736"
    },
    {
      "attachment": {},
      "manager": {
        "id": "1704233716",
        "name": "최*진"
      },
      "profile_id": "_xjYlxan",
      "author": {
        "status_message": "기초는 탄탄하게, 실전은 확실하게! 제로백 영어 베라쌤입니다",
        "active": true,
        "profile_image_url": "https://p.kakaocdn.net/th/talkp/wqcKBQivaa/JrQEq9TqEUT4645rxRuHtk/h98dxr_110x110_c.jpg",
        "chat_id": "4964159723615736",
        "user_type": 1,
        "nickname": "제로백 편입영어 베라쌤",
        "original_profile_image_url": "https://p.kakaocdn.net/talkp/wqcKBQivaa/JrQEq9TqEUT4645rxRuHtk/h98dxr.jpg",
        "id": "_xjYlxan",
        "full_profile_image_url": "https://p.kakaocdn.net/th/talkp/wqcKBQivaa/JrQEq9TqEUT4645rxRuHtk/h98dxr_640x640_s.jpg"
      },
      "supplement": {
        "muid": 1704233716
      },
      "send_at": 1770970970000,
      "id": "3775156885144316689",
      "type": 1,
      "author_id": "_xjYlxan",
      "message": "오오?!?! 징짜?! 너무 잘했네 ㅎㅎ 굿굿 채점해서 공유 해줘용!",
      "prev_id": "3775156559663878146",
      "chat_id": "4964159723615736"
    },
    {
      "attachment": {},
      "profile_id": "_xjYlxan",
      "author": {
        "status_message": "",
        "active": true,
        "profile_image_url": "",
        "chat_id": "4964159723615736",
        "user_type": 0,
        "nickname": "박수빈",
        "original_profile_image_url": "",
        "id": "4964159723615736_tuser",
        "full_profile_image_url": ""
      },
      "send_at": 1770971130000,
      "id": "3775158227663081474",
      "type": 1,
      "author_id": "4964159723615736_tuser",
      "message": "네! 군데 지굼 일중이라 끝나고 보내드릴게용! 문법도 7강까지 끝냈습니당",
      "prev_id": "3775156885144316689",
      "chat_id": "4964159723615736"
    },
    {
      "attachment": {},
      "manager": {
        "id": "1704233716",
        "name": "최*진"
      },
      "profile_id": "_xjYlxan",
      "author": {
        "status_message": "기초는 탄탄하게, 실전은 확실하게! 제로백 영어 베라쌤입니다",
        "active": true,
        "profile_image_url": "https://p.kakaocdn.net/th/talkp/wqcKBQivaa/JrQEq9TqEUT4645rxRuHtk/h98dxr_110x110_c.jpg",
        "chat_id": "4964159723615736",
        "user_type": 1,
        "nickname": "제로백 편입영어 베라쌤",
        "original_profile_image_url": "https://p.kakaocdn.net/talkp/wqcKBQivaa/JrQEq9TqEUT4645rxRuHtk/h98dxr.jpg",
        "id": "_xjYlxan",
        "full_profile_image_url": "https://p.kakaocdn.net/th/talkp/wqcKBQivaa/JrQEq9TqEUT4645rxRuHtk/h98dxr_640x640_s.jpg"
      },
      "supplement": {
        "muid": 1704233716
      },
      "send_at": 1770971370000,
      "id": "3775160237791064376",
      "type": 1,
      "author_id": "_xjYlxan",
      "message": "웅웅 알았어용!",
      "prev_id": "3775158227663081474",
      "chat_id": "4964159723615736"
    },
    {
      "attachment": {},
      "manager": {
        "id": "1704233716",
        "name": "최*진"
      },
      "profile_id": "_xjYlxan",
      "author": {
        "status_message": "기초는 탄탄하게, 실전은 확실하게! 제로백 영어 베라쌤입니다",
        "active": true,
        "profile_image_url": "https://p.kakaocdn.net/th/talkp/wqcKBQivaa/JrQEq9TqEUT4645rxRuHtk/h98dxr_110x110_c.jpg",
        "chat_id": "4964159723615736",
        "user_type": 1,
        "nickname": "제로백 편입영어 베라쌤",
        "original_profile_image_url": "https://p.kakaocdn.net/talkp/wqcKBQivaa/JrQEq9TqEUT4645rxRuHtk/h98dxr.jpg",
        "id": "_xjYlxan",
        "full_profile_image_url": "https://p.kakaocdn.net/th/talkp/wqcKBQivaa/JrQEq9TqEUT4645rxRuHtk/h98dxr_640x640_s.jpg"
      },
      "supplement": {
        "muid": 1704233716
      },
      "send_at": 1770971381000,
      "id": "3775160331041407124",
      "type": 1,
      "author_id": "_xjYlxan",
      "message": "화이팅하궁 😁😁😁",
      "prev_id": "3775160237791064376",
      "chat_id": "4964159723615736"
    },
    {
      "attachment": {},
      "profile_id": "_xjYlxan",
      "author": {
        "status_message": "",
        "active": true,
        "profile_image_url": "",
        "chat_id": "4964159723615736",
        "user_type": 0,
        "nickname": "박수빈",
        "original_profile_image_url": "",
        "id": "4964159723615736_tuser",
        "full_profile_image_url": ""
      },
      "send_at": 1770971576000,
      "id": "3775161969988882433",
      "type": 1,
      "author_id": "4964159723615736_tuser",
      "message": "넹 감사합니당ㅠ",
      "prev_id": "3775160331041407124",
      "chat_id": "4964159723615736"
    },
    {
      "attachment": {},
      "manager": {
        "id": "1704233716",
        "name": "최*진"
      },
      "profile_id": "_xjYlxan",
      "author": {
        "status_message": "기초는 탄탄하게, 실전은 확실하게! 제로백 영어 베라쌤입니다",
        "active": true,
        "profile_image_url": "https://p.kakaocdn.net/th/talkp/wqcKBQivaa/JrQEq9TqEUT4645rxRuHtk/h98dxr_110x110_c.jpg",
        "chat_id": "4964159723615736",
        "user_type": 1,
        "nickname": "제로백 편입영어 베라쌤",
        "original_profile_image_url": "https://p.kakaocdn.net/talkp/wqcKBQivaa/JrQEq9TqEUT4645rxRuHtk/h98dxr.jpg",
        "id": "_xjYlxan",
        "full_profile_image_url": "https://p.kakaocdn.net/th/talkp/wqcKBQivaa/JrQEq9TqEUT4645rxRuHtk/h98dxr_640x640_s.jpg"
      },
      "supplement": {
        "muid": 1704233716
      },
      "send_at": 1770971975000,
      "id": "3775165311127613580",
      "type": 1,
      "author_id": "_xjYlxan",
      "message": "😘😘😘",
      "prev_id": "3775161969988882433",
      "chat_id": "4964159723615736"
    },
    {
      "attachment": {},
      "manager": {
        "id": "1704233716",
        "name": "최*진"
      },
      "profile_id": "_xjYlxan",
      "author": {
        "status_message": "기초는 탄탄하게, 실전은 확실하게! 제로백 영어 베라쌤입니다",
        "active": true,
        "profile_image_url": "https://p.kakaocdn.net/th/talkp/wqcKBQivaa/JrQEq9TqEUT4645rxRuHtk/h98dxr_110x110_c.jpg",
        "chat_id": "4964159723615736",
        "user_type": 1,
        "nickname": "제로백 편입영어 베라쌤",
        "original_profile_image_url": "https://p.kakaocdn.net/talkp/wqcKBQivaa/JrQEq9TqEUT4645rxRuHtk/h98dxr.jpg",
        "id": "_xjYlxan",
        "full_profile_image_url": "https://p.kakaocdn.net/th/talkp/wqcKBQivaa/JrQEq9TqEUT4645rxRuHtk/h98dxr_640x640_s.jpg"
      },
      "supplement": {
        "muid": 1704233716
      },
      "send_at": 1770992496000,
      "id": "3775337454407481785",
      "type": 1,
      "author_id": "_xjYlxan",
      "message": "수빈이 자기전에 보내줘요!!",
      "prev_id": "3775165311127613580",
      "chat_id": "4964159723615736"
    },
    {
      "attachment": {
        "hl": [
          4691,
          4714
        ],
        "mtl": [
          "image/jpeg",
          "image/jpeg"
        ],
        "thumbnailWidths": [
          83,
          86
        ],
        "refreshUrl": "/profiles/_xjYlxan/chats/4964159723615736/chatlogs/3775343905376559105/imageUrls.json",
        "cmtl": [
          "",
          ""
        ],
        "secureThumbnailUrls": [
          "https://k.kakaocdn.net/dna/vhJpT/bl8NAFhLt7O/58OPt7RDGs25JiUtKZTl7B/i_7c84a23ba1e9.jpeg?credential=P2yoHVwtnqqJM5uful7K5Ufup3ht029u&expires=1771136004&allow_ip=&allow_referer=&signature=ilr2kmJ9Rkf0rBf%2BNkW6Q%2BAvVYM%3D&knm=i_7c84a23ba1e9.jpeg&convert=resize&w=83&h=120",
          "https://k.kakaocdn.net/dna/xwP5t/bl8NACk2IoK/w1BP8KmIGWp2cHBD5EOOtl/i_2f4667ada7d5.jpeg?credential=P2yoHVwtnqqJM5uful7K5Ufup3ht029u&expires=1771136004&allow_ip=&allow_referer=&signature=Hf8Jd%2FmqxAtXbImGl8FaQmonj%2BQ%3D&knm=i_2f4667ada7d5.jpeg&convert=resize&w=86&h=120"
        ],
        "secureImageUrls": [
          "https://k.kakaocdn.net/dna/vhJpT/bl8NAFhLt7O/rZIV33veh4rNWvK6UMIhwW/i_7c84a23ba1e9.jpeg?credential=P2yoHVwtnqqJM5uful7K5Ufup3ht029u&expires=1771136004&allow_ip=&allow_referer=&signature=G1vp%2BfFmTE3MkwpZjdJG5DlKiSI%3D&knm=i_7c84a23ba1e9.jpeg",
          "https://k.kakaocdn.net/dna/xwP5t/bl8NACk2IoK/xkYEQA2S2ePAc0vPMW39xn/i_2f4667ada7d5.jpeg?credential=P2yoHVwtnqqJM5uful7K5Ufup3ht029u&expires=1771136004&allow_ip=&allow_referer=&signature=OIDxBkPmxiLY4yJSztvjgMMbpnU%3D&knm=i_2f4667ada7d5.jpeg"
        ],
        "wl": [
          3212,
          3342
        ],
        "expire": 1865601264774,
        "sl": [
          3223772,
          2730968
        ],
        "csl": [
          "2a7355e08bd7ce217c56b4a4a23cddb3793c55ce",
          "2a0b2443fc10900ef26ea48302b5a7a0af15a7c4"
        ],
        "thumbnailHeights": [
          120,
          120
        ]
      },
      "profile_id": "_xjYlxan",
      "author": {
        "status_message": "",
        "active": true,
        "profile_image_url": "",
        "chat_id": "4964159723615736",
        "user_type": 0,
        "nickname": "박수빈",
        "original_profile_image_url": "",
        "id": "4964159723615736_tuser",
        "full_profile_image_url": ""
      },
      "send_at": 1770993265000,
      "id": "3775343905376559105",
      "type": 27,
      "author_id": "4964159723615736_tuser",
      "message": "사진 2장",
      "prev_id": "3775337454407481785",
      "chat_id": "4964159723615736"
    },
    {
      "attachment": {},
      "profile_id": "_xjYlxan",
      "author": {
        "status_message": "",
        "active": true,
        "profile_image_url": "",
        "chat_id": "4964159723615736",
        "user_type": 0,
        "nickname": "박수빈",
        "original_profile_image_url": "",
        "id": "4964159723615736_tuser",
        "full_profile_image_url": ""
      },
      "send_at": 1770993273000,
      "id": "3775343975874420738",
      "type": 1,
      "author_id": "4964159723615736_tuser",
      "message": "요깄습니당!",
      "prev_id": "3775343905376559105",
      "chat_id": "4964159723615736"
    },
    {
      "attachment": {},
      "manager": {
        "id": "1704233716",
        "name": "최*진"
      },
      "profile_id": "_xjYlxan",
      "author": {
        "status_message": "기초는 탄탄하게, 실전은 확실하게! 제로백 영어 베라쌤입니다",
        "active": true,
        "profile_image_url": "https://p.kakaocdn.net/th/talkp/wqcKBQivaa/JrQEq9TqEUT4645rxRuHtk/h98dxr_110x110_c.jpg",
        "chat_id": "4964159723615736",
        "user_type": 1,
        "nickname": "제로백 편입영어 베라쌤",
        "original_profile_image_url": "https://p.kakaocdn.net/talkp/wqcKBQivaa/JrQEq9TqEUT4645rxRuHtk/h98dxr.jpg",
        "id": "_xjYlxan",
        "full_profile_image_url": "https://p.kakaocdn.net/th/talkp/wqcKBQivaa/JrQEq9TqEUT4645rxRuHtk/h98dxr_640x640_s.jpg"
      },
      "supplement": {
        "muid": 1704233716
      },
      "send_at": 1770994651000,
      "id": "3775355532721748839",
      "type": 1,
      "author_id": "_xjYlxan",
      "message": "큐우 기다리구 잇엇다구 ㅜ 고생햇어요",
      "prev_id": "3775343975874420738",
      "chat_id": "4964159723615736"
    },
    {
      "attachment": {},
      "manager": {
        "id": "1704233716",
        "name": "최*진"
      },
      "profile_id": "_xjYlxan",
      "author": {
        "status_message": "기초는 탄탄하게, 실전은 확실하게! 제로백 영어 베라쌤입니다",
        "active": true,
        "profile_image_url": "https://p.kakaocdn.net/th/talkp/wqcKBQivaa/JrQEq9TqEUT4645rxRuHtk/h98dxr_110x110_c.jpg",
        "chat_id": "4964159723615736",
        "user_type": 1,
        "nickname": "제로백 편입영어 베라쌤",
        "original_profile_image_url": "https://p.kakaocdn.net/talkp/wqcKBQivaa/JrQEq9TqEUT4645rxRuHtk/h98dxr.jpg",
        "id": "_xjYlxan",
        "full_profile_image_url": "https://p.kakaocdn.net/th/talkp/wqcKBQivaa/JrQEq9TqEUT4645rxRuHtk/h98dxr_640x640_s.jpg"
      },
      "supplement": {
        "muid": 1704233716
      },
      "send_at": 1770994664000,
      "id": "3775355644265259385",
      "type": 1,
      "author_id": "_xjYlxan",
      "message": "오늘 구문 해꾸낭 ❤️❤️❤️",
      "prev_id": "3775355532721748839",
      "chat_id": "4964159723615736"
    },
    {
      "attachment": {},
      "manager": {
        "id": "1704233716",
        "name": "최*진"
      },
      "profile_id": "_xjYlxan",
      "author": {
        "status_message": "기초는 탄탄하게, 실전은 확실하게! 제로백 영어 베라쌤입니다",
        "active": true,
        "profile_image_url": "https://p.kakaocdn.net/th/talkp/wqcKBQivaa/JrQEq9TqEUT4645rxRuHtk/h98dxr_110x110_c.jpg",
        "chat_id": "4964159723615736",
        "user_type": 1,
        "nickname": "제로백 편입영어 베라쌤",
        "original_profile_image_url": "https://p.kakaocdn.net/talkp/wqcKBQivaa/JrQEq9TqEUT4645rxRuHtk/h98dxr.jpg",
        "id": "_xjYlxan",
        "full_profile_image_url": "https://p.kakaocdn.net/th/talkp/wqcKBQivaa/JrQEq9TqEUT4645rxRuHtk/h98dxr_640x640_s.jpg"
      },
      "supplement": {
        "muid": 1704233716
      },
      "send_at": 1770994677000,
      "id": "3775355747942445521",
      "type": 1,
      "author_id": "_xjYlxan",
      "message": "모르는건 없었옹?",
      "prev_id": "3775355644265259385",
      "chat_id": "4964159723615736"
    },
    {
      "attachment": {},
      "profile_id": "_xjYlxan",
      "author": {
        "status_message": "",
        "active": true,
        "profile_image_url": "",
        "chat_id": "4964159723615736",
        "user_type": 0,
        "nickname": "박수빈",
        "original_profile_image_url": "",
        "id": "4964159723615736_tuser",
        "full_profile_image_url": ""
      },
      "send_at": 1770995160000,
      "id": "3775359807590649858",
      "type": 1,
      "author_id": "4964159723615736_tuser",
      "message": "4강에서 6번이랑 10번 좀 헷갈렸어요ㅠ",
      "prev_id": "3775355747942445521",
      "chat_id": "4964159723615736"
    },
    {
      "attachment": {},
      "manager": {
        "id": "1704233716",
        "name": "최*진"
      },
      "profile_id": "_xjYlxan",
      "author": {
        "status_message": "기초는 탄탄하게, 실전은 확실하게! 제로백 영어 베라쌤입니다",
        "active": true,
        "profile_image_url": "https://p.kakaocdn.net/th/talkp/wqcKBQivaa/JrQEq9TqEUT4645rxRuHtk/h98dxr_110x110_c.jpg",
        "chat_id": "4964159723615736",
        "user_type": 1,
        "nickname": "제로백 편입영어 베라쌤",
        "original_profile_image_url": "https://p.kakaocdn.net/talkp/wqcKBQivaa/JrQEq9TqEUT4645rxRuHtk/h98dxr.jpg",
        "id": "_xjYlxan",
        "full_profile_image_url": "https://p.kakaocdn.net/th/talkp/wqcKBQivaa/JrQEq9TqEUT4645rxRuHtk/h98dxr_640x640_s.jpg"
      },
      "supplement": {
        "muid": 1704233716
      },
      "send_at": 1771026257000,
      "id": "3775620667398095663",
      "type": 1,
      "author_id": "_xjYlxan",
      "message": "목적어랑 목적격보어 부분이 조금 헷갈리나욤?!",
      "prev_id": "3775359807590649858",
      "chat_id": "4964159723615736"
    },
    {
      "attachment": {},
      "profile_id": "_xjYlxan",
      "author": {
        "status_message": "",
        "active": true,
        "profile_image_url": "",
        "chat_id": "4964159723615736",
        "user_type": 0,
        "nickname": "박수빈",
        "original_profile_image_url": "",
        "id": "4964159723615736_tuser",
        "full_profile_image_url": ""
      },
      "send_at": 1771045721000,
      "id": "3775783941734053889",
      "type": 1,
      "author_id": "4964159723615736_tuser",
      "message": "둘 다 2형식으로 생각을 했어요..! 뭔가 2형식으로 생각해도 해석이 되는 느낌..?이어서 헷갈렸던거 같아요!",
      "prev_id": "3775620667398095663",
      "chat_id": "4964159723615736"
    },
    {
      "attachment": {},
      "manager": {
        "id": "3677540646",
        "name": "김해민"
      },
      "profile_id": "_xjYlxan",
      "author": {
        "status_message": "기초는 탄탄하게, 실전은 확실하게! 제로백 영어 베라쌤입니다",
        "active": true,
        "profile_image_url": "https://p.kakaocdn.net/th/talkp/wqcKBQivaa/JrQEq9TqEUT4645rxRuHtk/h98dxr_110x110_c.jpg",
        "chat_id": "4964159723615736",
        "user_type": 1,
        "nickname": "제로백 편입영어 베라쌤",
        "original_profile_image_url": "https://p.kakaocdn.net/talkp/wqcKBQivaa/JrQEq9TqEUT4645rxRuHtk/h98dxr.jpg",
        "id": "_xjYlxan",
        "full_profile_image_url": "https://p.kakaocdn.net/th/talkp/wqcKBQivaa/JrQEq9TqEUT4645rxRuHtk/h98dxr_640x640_s.jpg"
      },
      "supplement": {
        "muid": 3677540646
      },
      "send_at": 1771047663000,
      "id": "3775800229989650249",
      "type": 1,
      "author_id": "_xjYlxan",
      "message": "아ㅋㅋㅋ이게 신기하게도 한국식 사고방식으로도 얼추 그대로 해석되는 경우들이 종종 있어서 그래용ㅋㅋ",
      "prev_id": "3775783941734053889",
      "chat_id": "4964159723615736"
    },
    {
      "attachment": {},
      "manager": {
        "id": "3677540646",
        "name": "김해민"
      },
      "profile_id": "_xjYlxan",
      "author": {
        "status_message": "기초는 탄탄하게, 실전은 확실하게! 제로백 영어 베라쌤입니다",
        "active": true,
        "profile_image_url": "https://p.kakaocdn.net/th/talkp/wqcKBQivaa/JrQEq9TqEUT4645rxRuHtk/h98dxr_110x110_c.jpg",
        "chat_id": "4964159723615736",
        "user_type": 1,
        "nickname": "제로백 편입영어 베라쌤",
        "original_profile_image_url": "https://p.kakaocdn.net/talkp/wqcKBQivaa/JrQEq9TqEUT4645rxRuHtk/h98dxr.jpg",
        "id": "_xjYlxan",
        "full_profile_image_url": "https://p.kakaocdn.net/th/talkp/wqcKBQivaa/JrQEq9TqEUT4645rxRuHtk/h98dxr_640x640_s.jpg"
      },
      "supplement": {
        "muid": 3677540646
      },
      "send_at": 1771047686000,
      "id": "3775800424886662980",
      "type": 1,
      "author_id": "_xjYlxan",
      "message": "계속 하다보면 감이 잡힐거양ㅎㅎ",
      "prev_id": "3775800229989650249",
      "chat_id": "4964159723615736"
    },
    {
      "attachment": {},
      "profile_id": "_xjYlxan",
      "author": {
        "status_message": "",
        "active": true,
        "profile_image_url": "",
        "chat_id": "4964159723615736",
        "user_type": 0,
        "nickname": "박수빈",
        "original_profile_image_url": "",
        "id": "4964159723615736_tuser",
        "full_profile_image_url": ""
      },
      "send_at": 1771069563000,
      "id": "3775983943151906817",
      "type": 1,
      "author_id": "4964159723615736_tuser",
      "message": "넹!",
      "prev_id": "3775800424886662980",
      "chat_id": "4964159723615736"
    },
    {
      "attachment": {},
      "manager": {
        "id": "1704233716",
        "name": "최*진"
      },
      "profile_id": "_xjYlxan",
      "author": {
        "status_message": "기초는 탄탄하게, 실전은 확실하게! 제로백 영어 베라쌤입니다",
        "active": true,
        "profile_image_url": "https://p.kakaocdn.net/th/talkp/wqcKBQivaa/JrQEq9TqEUT4645rxRuHtk/h98dxr_110x110_c.jpg",
        "chat_id": "4964159723615736",
        "user_type": 1,
        "nickname": "제로백 편입영어 베라쌤",
        "original_profile_image_url": "https://p.kakaocdn.net/talkp/wqcKBQivaa/JrQEq9TqEUT4645rxRuHtk/h98dxr.jpg",
        "id": "_xjYlxan",
        "full_profile_image_url": "https://p.kakaocdn.net/th/talkp/wqcKBQivaa/JrQEq9TqEUT4645rxRuHtk/h98dxr_640x640_s.jpg"
      },
      "supplement": {
        "muid": 1704233716
      },
      "send_at": 1771071163000,
      "id": "3775997363017140250",
      "type": 1,
      "author_id": "_xjYlxan",
      "message": "웅웅 힘내구 ! 오늘 끝까지 잘 마감해보장",
      "prev_id": "3775983943151906817",
      "chat_id": "4964159723615736"
    },
    {
      "attachment": {},
      "manager": {
        "id": "1704233716",
        "name": "최*진"
      },
      "profile_id": "_xjYlxan",
      "author": {
        "status_message": "기초는 탄탄하게, 실전은 확실하게! 제로백 영어 베라쌤입니다",
        "active": true,
        "profile_image_url": "https://p.kakaocdn.net/th/talkp/wqcKBQivaa/JrQEq9TqEUT4645rxRuHtk/h98dxr_110x110_c.jpg",
        "chat_id": "4964159723615736",
        "user_type": 1,
        "nickname": "제로백 편입영어 베라쌤",
        "original_profile_image_url": "https://p.kakaocdn.net/talkp/wqcKBQivaa/JrQEq9TqEUT4645rxRuHtk/h98dxr.jpg",
        "id": "_xjYlxan",
        "full_profile_image_url": "https://p.kakaocdn.net/th/talkp/wqcKBQivaa/JrQEq9TqEUT4645rxRuHtk/h98dxr_640x640_s.jpg"
      },
      "supplement": {
        "muid": 1704233716
      },
      "send_at": 1771128336000,
      "id": "3776476965662355214",
      "type": 1,
      "author_id": "_xjYlxan",
      "message": "수빈아 잘 햇엉 어제?",
      "prev_id": "3775997363017140250",
      "chat_id": "4964159723615736"
    }
  ],
  "has_next": false
}