{
  "url": "https://kmong.com/signup-seller",
  "title": "실력 있는 전문가 찾기, 크몽",
  "text": "본인인증하면\n전문가 등록완료!\n본인인증\n휴대폰 본인인증\n전문가 약관동의\n크몽 판매 이용약관에 동의합니다. (필수)\n전문가 등록 완료\n이미 전문가로 동의하셨습니다.\n돌아가기",
  "inputs": [
    {
      "tag": "INPUT",
      "type": "checkbox",
      "name": "",
      "placeholder": "",
      "id": "",
      "value": "on",
      "visible": true
    }
  ],
  "buttons": [
    "휴대폰 본인인증",
    "전문가 등록 완료",
    "×",
    "아니요",
    "아니요",
    "돌아가기"
  ],
  "fileInputs": [
    {
      "name": "",
      "accept": "",
      "id": "",
      "multiple": false
    }
  ]
}